native/wpilib/_init_robotpy_native_wpilib.py
native/wpilib/robotpy-native-wpilib.pc
native/wpilib/include/LICENSE.md
native/wpilib/include/ThirdPartyNotices.txt
native/wpilib/include/WPILibVersion.h
native/wpilib/include/frc/ADIS16448_IMU.h
native/wpilib/include/frc/ADIS16470_IMU.h
native/wpilib/include/frc/ADXL345_I2C.h
native/wpilib/include/frc/ADXL345_SPI.h
native/wpilib/include/frc/ADXL362.h
native/wpilib/include/frc/ADXRS450_Gyro.h
native/wpilib/include/frc/AddressableLED.h
native/wpilib/include/frc/Alert.h
native/wpilib/include/frc/AnalogAccelerometer.h
native/wpilib/include/frc/AnalogEncoder.h
native/wpilib/include/frc/AnalogGyro.h
native/wpilib/include/frc/AnalogInput.h
native/wpilib/include/frc/AnalogOutput.h
native/wpilib/include/frc/AnalogPotentiometer.h
native/wpilib/include/frc/AnalogTrigger.h
native/wpilib/include/frc/AnalogTriggerOutput.h
native/wpilib/include/frc/AnalogTriggerType.h
native/wpilib/include/frc/AsynchronousInterrupt.h
native/wpilib/include/frc/BuiltInAccelerometer.h
native/wpilib/include/frc/CAN.h
native/wpilib/include/frc/Compressor.h
native/wpilib/include/frc/CompressorConfigType.h
native/wpilib/include/frc/Counter.h
native/wpilib/include/frc/CounterBase.h
native/wpilib/include/frc/DMA.h
native/wpilib/include/frc/DMASample.h
native/wpilib/include/frc/DSControlWord.h
native/wpilib/include/frc/DataLogManager.h
native/wpilib/include/frc/DigitalGlitchFilter.h
native/wpilib/include/frc/DigitalInput.h
native/wpilib/include/frc/DigitalOutput.h
native/wpilib/include/frc/DigitalSource.h
native/wpilib/include/frc/DoubleSolenoid.h
native/wpilib/include/frc/DriverStation.h
native/wpilib/include/frc/DutyCycle.h
native/wpilib/include/frc/DutyCycleEncoder.h
native/wpilib/include/frc/Encoder.h
native/wpilib/include/frc/Errors.h
native/wpilib/include/frc/Filesystem.h
native/wpilib/include/frc/GenericHID.h
native/wpilib/include/frc/I2C.h
native/wpilib/include/frc/IterativeRobotBase.h
native/wpilib/include/frc/Joystick.h
robotpy_native_wpilib-2025.3.2.dist-info/METADATA
robotpy_native_wpilib-2025.3.2.dist-info/WHEEL
robotpy_native_wpilib-2025.3.2.dist-info/entry_points.txt
robotpy_native_wpilib-2025.3.2.dist-info/RECORD
