Metadata-Version: 2.4
Name: robotpy-native-wpilib
Version: 2025.3.2
Summary: WPILib Robotics Library
License-Expression: BSD-3-Clause
Requires-Dist: robotpy-native-ntcore==2025.3.2
Requires-Dist: robotpy-native-wpihal==2025.3.2
Requires-Dist: robotpy-native-wpimath==2025.3.2
Requires-Dist: robotpy-native-wpinet==2025.3.2
Requires-Dist: robotpy-native-wpiutil==2025.3.2
